lovely_prompts/__init__.py
lovely_prompts/_modidx.py
lovely_prompts/core.py
lovely_prompts-0.0.1.dist-info/LICENSE
lovely_prompts-0.0.1.dist-info/METADATA
lovely_prompts-0.0.1.dist-info/WHEEL
lovely_prompts-0.0.1.dist-info/entry_points.txt
lovely_prompts-0.0.1.dist-info/top_level.txt
lovely_prompts-0.0.1.dist-info/RECORD
